spectrumtext/__init__.py
spectrumtext/colors.py
spectrumtext/exceptions.py
spectrumtext/printer.py
spectrumtext/spectrumtext.py
spectrumtext-0.1.2.dist-info/LICENSE
spectrumtext-0.1.2.dist-info/METADATA
spectrumtext-0.1.2.dist-info/WHEEL
spectrumtext-0.1.2.dist-info/top_level.txt
spectrumtext-0.1.2.dist-info/RECORD
